{
  "fixtures": [
    {
      "id": 43,
      "code": 2270069,
      "team_h": 16,
      "team_h_score": null,
      "team_a": 5,
      "team_a_score": null,
      "event": 6,
      "finished": false,
      "minutes": 0,
      "provisional_start_time": false,
      "kickoff_time": "2022-05-01T13:00:00Z",
      "event_name": "Omg\u00e5ng 6",
      "is_home": false
    },
    {
      "id": 56,
      "code": 2270078,
      "team_h": 5,
      "team_h_score": null,
      "team_a": 7,
      "team_a_score": null,
      "event": 7,
      "finished": false,
      "minutes": 0,
      "provisional_start_time": false,
      "kickoff_time": "2022-05-09T17:10:00Z",
      "event_name": "Omg\u00e5ng 7",
      "is_home": true
    },
    {
      "id": 59,
      "code": 2270090,
      "team_h": 3,
      "team_h_score": null,
      "team_a": 5,
      "team_a_score": null,
      "event": 8,
      "finished": false,
      "minutes": 0,
      "provisional_start_time": false,
      "kickoff_time": "2022-05-14T15:30:00Z",
      "event_name": "Omg\u00e5ng 8",
      "is_home": false
    },
    {
      "id": 69,
      "code": 2270095,
      "team_h": 5,
      "team_h_score": null,
      "team_a": 4,
      "team_a_score": null,
      "event": 9,
      "finished": false,
      "minutes": 0,
      "provisional_start_time": false,
      "kickoff_time": "2022-05-22T13:00:00Z",
      "event_name": "Omg\u00e5ng 9",
      "is_home": true
    },
    {
      "id": 81,
      "code": 2270105,
      "team_h": 9,
      "team_h_score": null,
      "team_a": 5,
      "team_a_score": null,
      "event": 10,
      "finished": false,
      "minutes": 0,
      "provisional_start_time": false,
      "kickoff_time": "2022-05-29T13:00:00Z",
      "event_name": "Omg\u00e5ng 10",
      "is_home": false
    },
    {
      "id": 86,
      "code": 2270110,
      "team_h": 5,
      "team_h_score": null,
      "team_a": 13,
      "team_a_score": null,
      "event": 11,
      "finished": false,
      "minutes": 0,
      "provisional_start_time": false,
      "kickoff_time": "2022-06-27T17:00:00Z",
      "event_name": "Omg\u00e5ng 11",
      "is_home": true
    },
    {
      "id": 92,
      "code": 2270117,
      "team_h": 6,
      "team_h_score": null,
      "team_a": 5,
      "team_a_score": null,
      "event": 12,
      "finished": false,
      "minutes": 0,
      "provisional_start_time": false,
      "kickoff_time": "2022-07-02T23:00:00Z",
      "event_name": "Omg\u00e5ng 12",
      "is_home": false
    },
    {
      "id": 102,
      "code": 2270127,
      "team_h": 5,
      "team_h_score": null,
      "team_a": 12,
      "team_a_score": null,
      "event": 13,
      "finished": false,
      "minutes": 0,
      "provisional_start_time": false,
      "kickoff_time": "2022-07-09T23:00:00Z",
      "event_name": "Omg\u00e5ng 13",
      "is_home": true
    },
    {
      "id": 110,
      "code": 2270134,
      "team_h": 2,
      "team_h_score": null,
      "team_a": 5,
      "team_a_score": null,
      "event": 14,
      "finished": false,
      "minutes": 0,
      "provisional_start_time": false,
      "kickoff_time": "2022-07-16T23:00:00Z",
      "event_name": "Omg\u00e5ng 14",
      "is_home": false
    },
    {
      "id": 119,
      "code": 2270144,
      "team_h": 10,
      "team_h_score": null,
      "team_a": 5,
      "team_a_score": null,
      "event": 15,
      "finished": false,
      "minutes": 0,
      "provisional_start_time": false,
      "kickoff_time": "2022-07-23T23:00:00Z",
      "event_name": "Omg\u00e5ng 15",
      "is_home": false
    },
    {
      "id": 126,
      "code": 2270152,
      "team_h": 5,
      "team_h_score": null,
      "team_a": 6,
      "team_a_score": null,
      "event": 16,
      "finished": false,
      "minutes": 0,
      "provisional_start_time": false,
      "kickoff_time": "2022-07-30T23:00:00Z",
      "event_name": "Omg\u00e5ng 16",
      "is_home": true
    },
    {
      "id": 135,
      "code": 2270162,
      "team_h": 14,
      "team_h_score": null,
      "team_a": 5,
      "team_a_score": null,
      "event": 17,
      "finished": false,
      "minutes": 0,
      "provisional_start_time": false,
      "kickoff_time": "2022-08-06T23:00:00Z",
      "event_name": "Omg\u00e5ng 17",
      "is_home": false
    },
    {
      "id": 142,
      "code": 2270169,
      "team_h": 5,
      "team_h_score": null,
      "team_a": 9,
      "team_a_score": null,
      "event": 18,
      "finished": false,
      "minutes": 0,
      "provisional_start_time": false,
      "kickoff_time": "2022-08-13T23:00:00Z",
      "event_name": "Omg\u00e5ng 18",
      "is_home": true
    },
    {
      "id": 148,
      "code": 2270174,
      "team_h": 18,
      "team_h_score": null,
      "team_a": 5,
      "team_a_score": null,
      "event": 19,
      "finished": false,
      "minutes": 0,
      "provisional_start_time": false,
      "kickoff_time": "2022-08-20T23:00:00Z",
      "event_name": "Omg\u00e5ng 19",
      "is_home": false
    },
    {
      "id": 156,
      "code": 2270183,
      "team_h": 7,
      "team_h_score": null,
      "team_a": 5,
      "team_a_score": null,
      "event": 20,
      "finished": false,
      "minutes": 0,
      "provisional_start_time": false,
      "kickoff_time": "2022-08-27T23:00:00Z",
      "event_name": "Omg\u00e5ng 20",
      "is_home": false
    },
    {
      "id": 163,
      "code": 2270190,
      "team_h": 5,
      "team_h_score": null,
      "team_a": 1,
      "team_a_score": null,
      "event": 21,
      "finished": false,
      "minutes": 0,
      "provisional_start_time": false,
      "kickoff_time": "2022-09-03T23:00:00Z",
      "event_name": "Omg\u00e5ng 21",
      "is_home": true
    },
    {
      "id": 170,
      "code": 2270202,
      "team_h": 17,
      "team_h_score": null,
      "team_a": 5,
      "team_a_score": null,
      "event": 22,
      "finished": false,
      "minutes": 0,
      "provisional_start_time": false,
      "kickoff_time": "2022-09-10T23:00:00Z",
      "event_name": "Omg\u00e5ng 22",
      "is_home": false
    },
    {
      "id": 181,
      "code": 2270208,
      "team_h": 5,
      "team_h_score": null,
      "team_a": 3,
      "team_a_score": null,
      "event": 23,
      "finished": false,
      "minutes": 0,
      "provisional_start_time": false,
      "kickoff_time": "2022-09-17T23:00:00Z",
      "event_name": "Omg\u00e5ng 23",
      "is_home": true
    },
    {
      "id": 187,
      "code": 2270213,
      "team_h": 4,
      "team_h_score": null,
      "team_a": 5,
      "team_a_score": null,
      "event": 24,
      "finished": false,
      "minutes": 0,
      "provisional_start_time": false,
      "kickoff_time": "2022-10-01T23:00:00Z",
      "event_name": "Omg\u00e5ng 24",
      "is_home": false
    },
    {
      "id": 198,
      "code": 2270224,
      "team_h": 5,
      "team_h_score": null,
      "team_a": 10,
      "team_a_score": null,
      "event": 25,
      "finished": false,
      "minutes": 0,
      "provisional_start_time": false,
      "kickoff_time": "2022-10-08T23:00:00Z",
      "event_name": "Omg\u00e5ng 25",
      "is_home": true
    },
    {
      "id": 204,
      "code": 2270231,
      "team_h": 5,
      "team_h_score": null,
      "team_a": 16,
      "team_a_score": null,
      "event": 26,
      "finished": false,
      "minutes": 0,
      "provisional_start_time": false,
      "kickoff_time": "2022-10-15T23:00:00Z",
      "event_name": "Omg\u00e5ng 26",
      "is_home": true
    },
    {
      "id": 216,
      "code": 2270243,
      "team_h": 13,
      "team_h_score": null,
      "team_a": 5,
      "team_a_score": null,
      "event": 27,
      "finished": false,
      "minutes": 0,
      "provisional_start_time": false,
      "kickoff_time": "2022-10-18T23:00:00Z",
      "event_name": "Omg\u00e5ng 27",
      "is_home": false
    },
    {
      "id": 220,
      "code": 2270247,
      "team_h": 5,
      "team_h_score": null,
      "team_a": 2,
      "team_a_score": null,
      "event": 28,
      "finished": false,
      "minutes": 0,
      "provisional_start_time": false,
      "kickoff_time": "2022-10-22T23:00:00Z",
      "event_name": "Omg\u00e5ng 28",
      "is_home": true
    },
    {
      "id": 228,
      "code": 2270254,
      "team_h": 5,
      "team_h_score": null,
      "team_a": 19,
      "team_a_score": null,
      "event": 29,
      "finished": false,
      "minutes": 0,
      "provisional_start_time": false,
      "kickoff_time": "2022-10-29T23:00:00Z",
      "event_name": "Omg\u00e5ng 29",
      "is_home": true
    },
    {
      "id": 233,
      "code": 2270260,
      "team_h": 12,
      "team_h_score": null,
      "team_a": 5,
      "team_a_score": null,
      "event": 30,
      "finished": false,
      "minutes": 0,
      "provisional_start_time": false,
      "kickoff_time": "2022-11-06T00:00:00Z",
      "event_name": "Omg\u00e5ng 30",
      "is_home": false
    }
  ],
  "history": [
    {
      "element": 183,
      "fixture": 8,
      "opponent_team": 14,
      "total_points": 2,
      "was_home": true,
      "kickoff_time": "2022-04-04T17:00:00Z",
      "team_h_score": 0,
      "team_a_score": 2,
      "round": 1,
      "minutes": 67,
      "goals_scored": 0,
      "assists": 0,
      "clean_sheets": 0,
      "goals_conceded": 2,
      "penalties_saved": 0,
      "penalties_missed": 0,
      "yellow_cards": 0,
      "red_cards": 0,
      "saves": 0,
      "own_goals": 0,
      "attacking_bonus": 0,
      "defending_bonus": 1,
      "winning_goals": 0,
      "crosses": 0,
      "key_passes": 0,
      "big_chances_created": 0,
      "clearances_blocks_interceptions": 13,
      "recoveries": 5,
      "value": 55,
      "transfers_balance": 0,
      "selected": 481,
      "transfers_in": 0,
      "transfers_out": 0
    },
    {
      "element": 183,
      "fixture": 16,
      "opponent_team": 1,
      "total_points": 3,
      "was_home": false,
      "kickoff_time": "2022-04-11T17:10:00Z",
      "team_h_score": 1,
      "team_a_score": 1,
      "round": 2,
      "minutes": 90,
      "goals_scored": 0,
      "assists": 0,
      "clean_sheets": 0,
      "goals_conceded": 1,
      "penalties_saved": 0,
      "penalties_missed": 0,
      "yellow_cards": 0,
      "red_cards": 0,
      "saves": 0,
      "own_goals": 0,
      "attacking_bonus": 0,
      "defending_bonus": 1,
      "winning_goals": 0,
      "crosses": 0,
      "key_passes": 0,
      "big_chances_created": 0,
      "clearances_blocks_interceptions": 8,
      "recoveries": 6,
      "value": 55,
      "transfers_balance": -23,
      "selected": 466,
      "transfers_in": 11,
      "transfers_out": 34
    },
    {
      "element": 183,
      "fixture": 21,
      "opponent_team": 18,
      "total_points": 0,
      "was_home": true,
      "kickoff_time": "2022-04-17T15:30:00Z",
      "team_h_score": 4,
      "team_a_score": 1,
      "round": 3,
      "minutes": 0,
      "goals_scored": 0,
      "assists": 0,
      "clean_sheets": 0,
      "goals_conceded": 0,
      "penalties_saved": 0,
      "penalties_missed": 0,
      "yellow_cards": 0,
      "red_cards": 0,
      "saves": 0,
      "own_goals": 0,
      "attacking_bonus": 0,
      "defending_bonus": 0,
      "winning_goals": 0,
      "crosses": 0,
      "key_passes": 0,
      "big_chances_created": 0,
      "clearances_blocks_interceptions": 0,
      "recoveries": 0,
      "value": 55,
      "transfers_balance": 80,
      "selected": 553,
      "transfers_in": 104,
      "transfers_out": 24
    },
    {
      "element": 183,
      "fixture": 31,
      "opponent_team": 19,
      "total_points": 0,
      "was_home": false,
      "kickoff_time": "2022-04-21T17:00:00Z",
      "team_h_score": 1,
      "team_a_score": 0,
      "round": 4,
      "minutes": 0,
      "goals_scored": 0,
      "assists": 0,
      "clean_sheets": 0,
      "goals_conceded": 0,
      "penalties_saved": 0,
      "penalties_missed": 0,
      "yellow_cards": 0,
      "red_cards": 0,
      "saves": 0,
      "own_goals": 0,
      "attacking_bonus": 0,
      "defending_bonus": 0,
      "winning_goals": 0,
      "crosses": 0,
      "key_passes": 0,
      "big_chances_created": 0,
      "clearances_blocks_interceptions": 0,
      "recoveries": 0,
      "value": 55,
      "transfers_balance": -56,
      "selected": 495,
      "transfers_in": 9,
      "transfers_out": 65
    },
    {
      "element": 183,
      "fixture": 36,
      "opponent_team": 17,
      "total_points": 0,
      "was_home": true,
      "kickoff_time": "2022-04-25T17:00:00Z",
      "team_h_score": 3,
      "team_a_score": 1,
      "round": 5,
      "minutes": 0,
      "goals_scored": 0,
      "assists": 0,
      "clean_sheets": 0,
      "goals_conceded": 0,
      "penalties_saved": 0,
      "penalties_missed": 0,
      "yellow_cards": 0,
      "red_cards": 0,
      "saves": 0,
      "own_goals": 0,
      "attacking_bonus": 0,
      "defending_bonus": 0,
      "winning_goals": 0,
      "crosses": 0,
      "key_passes": 0,
      "big_chances_created": 0,
      "clearances_blocks_interceptions": 0,
      "recoveries": 0,
      "value": 55,
      "transfers_balance": -74,
      "selected": 424,
      "transfers_in": 1,
      "transfers_out": 75
    }
  ],
  "history_past": [
    {
      "season_name": "2021",
      "element_code": 432876,
      "start_cost": 55,
      "end_cost": 53,
      "total_points": 90,
      "minutes": 1623,
      "goals_scored": 1,
      "assists": 1,
      "clean_sheets": 9,
      "goals_conceded": 17,
      "penalties_saved": 0,
      "penalties_missed": 0,
      "yellow_cards": 1,
      "red_cards": 1,
      "saves": 0,
      "own_goals": 0,
      "attacking_bonus": 0,
      "defending_bonus": 18,
      "winning_goals": 0,
      "crosses": 1,
      "key_passes": 2,
      "big_chances_created": 0,
      "clearances_blocks_interceptions": 96,
      "recoveries": 107
    }
  ]
}