{
  "fixtures": [
    {
      "id": 231,
      "code": 2417466,
      "team_h": 9,
      "team_h_score": null,
      "team_a": 12,
      "team_a_score": null,
      "event": 29,
      "finished": false,
      "minutes": 0,
      "provisional_start_time": false,
      "kickoff_time": "2024-11-04T18:10:00Z",
      "event_name": "Omg\u00e5ng 29",
      "is_home": true
    },
    {
      "id": 234,
      "code": 2417473,
      "team_h": 7,
      "team_h_score": null,
      "team_a": 9,
      "team_a_score": null,
      "event": 30,
      "finished": false,
      "minutes": 0,
      "provisional_start_time": false,
      "kickoff_time": "2024-11-10T14:00:00Z",
      "event_name": "Omg\u00e5ng 30",
      "is_home": false
    }
  ],
  "history": [
    {
      "element": 210,
      "fixture": 1,
      "opponent_team": 1,
      "total_points": 1,
      "was_home": true,
      "kickoff_time": "2024-03-30T14:00:00Z",
      "team_h_score": 1,
      "team_a_score": 5,
      "round": 1,
      "minutes": 19,
      "goals_scored": 0,
      "assists": 0,
      "clean_sheets": 0,
      "goals_conceded": 1,
      "penalties_saved": 0,
      "penalties_missed": 0,
      "yellow_cards": 0,
      "red_cards": 0,
      "saves": 0,
      "own_goals": 0,
      "attacking_bonus": 0,
      "defending_bonus": 0,
      "winning_goals": 0,
      "key_passes": 0,
      "clearances_blocks_interceptions": 1,
      "value": 85,
      "transfers_balance": 0,
      "selected": 6724,
      "transfers_in": 0,
      "transfers_out": 0
    },
    {
      "element": 210,
      "fixture": 10,
      "opponent_team": 14,
      "total_points": 2,
      "was_home": false,
      "kickoff_time": "2024-04-06T15:30:00Z",
      "team_h_score": 3,
      "team_a_score": 0,
      "round": 2,
      "minutes": 78,
      "goals_scored": 0,
      "assists": 0,
      "clean_sheets": 0,
      "goals_conceded": 3,
      "penalties_saved": 0,
      "penalties_missed": 0,
      "yellow_cards": 0,
      "red_cards": 0,
      "saves": 0,
      "own_goals": 0,
      "attacking_bonus": 0,
      "defending_bonus": 0,
      "winning_goals": 0,
      "key_passes": 1,
      "clearances_blocks_interceptions": 7,
      "value": 85,
      "transfers_balance": -416,
      "selected": 6595,
      "transfers_in": 117,
      "transfers_out": 533
    },
    {
      "element": 210,
      "fixture": 21,
      "opponent_team": 31,
      "total_points": 2,
      "was_home": true,
      "kickoff_time": "2024-04-14T12:00:00Z",
      "team_h_score": 1,
      "team_a_score": 0,
      "round": 3,
      "minutes": 90,
      "goals_scored": 0,
      "assists": 0,
      "clean_sheets": 1,
      "goals_conceded": 0,
      "penalties_saved": 0,
      "penalties_missed": 0,
      "yellow_cards": 0,
      "red_cards": 0,
      "saves": 0,
      "own_goals": 0,
      "attacking_bonus": 0,
      "defending_bonus": 0,
      "winning_goals": 0,
      "key_passes": 0,
      "clearances_blocks_interceptions": 4,
      "value": 84,
      "transfers_balance": -894,
      "selected": 5749,
      "transfers_in": 141,
      "transfers_out": 1035
    },
    {
      "element": 210,
      "fixture": 25,
      "opponent_team": 4,
      "total_points": 2,
      "was_home": false,
      "kickoff_time": "2024-04-20T13:10:00Z",
      "team_h_score": 1,
      "team_a_score": 1,
      "round": 4,
      "minutes": 90,
      "goals_scored": 0,
      "assists": 0,
      "clean_sheets": 0,
      "goals_conceded": 1,
      "penalties_saved": 0,
      "penalties_missed": 0,
      "yellow_cards": 0,
      "red_cards": 0,
      "saves": 0,
      "own_goals": 0,
      "attacking_bonus": 0,
      "defending_bonus": 0,
      "winning_goals": 0,
      "key_passes": 1,
      "clearances_blocks_interceptions": 4,
      "value": 84,
      "transfers_balance": -937,
      "selected": 4828,
      "transfers_in": 17,
      "transfers_out": 954
    },
    {
      "element": 210,
      "fixture": 39,
      "opponent_team": 5,
      "total_points": 13,
      "was_home": true,
      "kickoff_time": "2024-04-25T17:00:00Z",
      "team_h_score": 4,
      "team_a_score": 2,
      "round": 5,
      "minutes": 87,
      "goals_scored": 2,
      "assists": 0,
      "clean_sheets": 0,
      "goals_conceded": 2,
      "penalties_saved": 0,
      "penalties_missed": 0,
      "yellow_cards": 0,
      "red_cards": 0,
      "saves": 0,
      "own_goals": 0,
      "attacking_bonus": 0,
      "defending_bonus": 0,
      "winning_goals": 1,
      "key_passes": 0,
      "clearances_blocks_interceptions": 2,
      "value": 83,
      "transfers_balance": -332,
      "selected": 4521,
      "transfers_in": 22,
      "transfers_out": 354
    },
    {
      "element": 210,
      "fixture": 42,
      "opponent_team": 6,
      "total_points": 6,
      "was_home": false,
      "kickoff_time": "2024-04-28T14:30:00Z",
      "team_h_score": 1,
      "team_a_score": 2,
      "round": 6,
      "minutes": 65,
      "goals_scored": 0,
      "assists": 1,
      "clean_sheets": 0,
      "goals_conceded": 1,
      "penalties_saved": 0,
      "penalties_missed": 0,
      "yellow_cards": 0,
      "red_cards": 0,
      "saves": 0,
      "own_goals": 0,
      "attacking_bonus": 1,
      "defending_bonus": 0,
      "winning_goals": 0,
      "key_passes": 2,
      "clearances_blocks_interceptions": 4,
      "value": 83,
      "transfers_balance": 267,
      "selected": 4817,
      "transfers_in": 351,
      "transfers_out": 84
    },
    {
      "element": 210,
      "fixture": 52,
      "opponent_team": 12,
      "total_points": 7,
      "was_home": false,
      "kickoff_time": "2024-05-05T14:30:00Z",
      "team_h_score": 6,
      "team_a_score": 2,
      "round": 7,
      "minutes": 90,
      "goals_scored": 1,
      "assists": 0,
      "clean_sheets": 0,
      "goals_conceded": 6,
      "penalties_saved": 0,
      "penalties_missed": 0,
      "yellow_cards": 0,
      "red_cards": 0,
      "saves": 0,
      "own_goals": 0,
      "attacking_bonus": 0,
      "defending_bonus": 0,
      "winning_goals": 0,
      "key_passes": 0,
      "clearances_blocks_interceptions": 1,
      "value": 83,
      "transfers_balance": 226,
      "selected": 5064,
      "transfers_in": 337,
      "transfers_out": 111
    },
    {
      "element": 210,
      "fixture": 62,
      "opponent_team": 2,
      "total_points": 4,
      "was_home": true,
      "kickoff_time": "2024-05-12T12:00:00Z",
      "team_h_score": 1,
      "team_a_score": 2,
      "round": 8,
      "minutes": 90,
      "goals_scored": 0,
      "assists": 0,
      "clean_sheets": 0,
      "goals_conceded": 2,
      "penalties_saved": 0,
      "penalties_missed": 0,
      "yellow_cards": 0,
      "red_cards": 0,
      "saves": 0,
      "own_goals": 0,
      "attacking_bonus": 2,
      "defending_bonus": 0,
      "winning_goals": 0,
      "key_passes": 4,
      "clearances_blocks_interceptions": 7,
      "value": 83,
      "transfers_balance": 243,
      "selected": 5351,
      "transfers_in": 335,
      "transfers_out": 92
    },
    {
      "element": 210,
      "fixture": 70,
      "opponent_team": 10,
      "total_points": 2,
      "was_home": false,
      "kickoff_time": "2024-05-16T17:00:00Z",
      "team_h_score": 1,
      "team_a_score": 1,
      "round": 9,
      "minutes": 90,
      "goals_scored": 0,
      "assists": 0,
      "clean_sheets": 0,
      "goals_conceded": 1,
      "penalties_saved": 0,
      "penalties_missed": 0,
      "yellow_cards": 0,
      "red_cards": 0,
      "saves": 0,
      "own_goals": 0,
      "attacking_bonus": 0,
      "defending_bonus": 0,
      "winning_goals": 0,
      "key_passes": 1,
      "clearances_blocks_interceptions": 3,
      "value": 83,
      "transfers_balance": -33,
      "selected": 5337,
      "transfers_in": 102,
      "transfers_out": 135
    },
    {
      "element": 210,
      "fixture": 73,
      "opponent_team": 21,
      "total_points": 6,
      "was_home": false,
      "kickoff_time": "2024-05-19T12:00:00Z",
      "team_h_score": 2,
      "team_a_score": 1,
      "round": 10,
      "minutes": 90,
      "goals_scored": 1,
      "assists": 0,
      "clean_sheets": 0,
      "goals_conceded": 2,
      "penalties_saved": 0,
      "penalties_missed": 0,
      "yellow_cards": 1,
      "red_cards": 0,
      "saves": 0,
      "own_goals": 0,
      "attacking_bonus": 0,
      "defending_bonus": 0,
      "winning_goals": 0,
      "key_passes": 0,
      "clearances_blocks_interceptions": 3,
      "value": 83,
      "transfers_balance": -137,
      "selected": 5209,
      "transfers_in": 61,
      "transfers_out": 198
    },
    {
      "element": 210,
      "fixture": 88,
      "opponent_team": 18,
      "total_points": 2,
      "was_home": true,
      "kickoff_time": "2024-05-27T17:00:00Z",
      "team_h_score": 0,
      "team_a_score": 4,
      "round": 11,
      "minutes": 83,
      "goals_scored": 0,
      "assists": 0,
      "clean_sheets": 0,
      "goals_conceded": 3,
      "penalties_saved": 0,
      "penalties_missed": 0,
      "yellow_cards": 0,
      "red_cards": 0,
      "saves": 0,
      "own_goals": 0,
      "attacking_bonus": 0,
      "defending_bonus": 0,
      "winning_goals": 0,
      "key_passes": 1,
      "clearances_blocks_interceptions": 3,
      "value": 83,
      "transfers_balance": -94,
      "selected": 4992,
      "transfers_in": 57,
      "transfers_out": 151
    },
    {
      "element": 210,
      "fixture": 94,
      "opponent_team": 3,
      "total_points": 2,
      "was_home": false,
      "kickoff_time": "2024-06-01T15:30:00Z",
      "team_h_score": 5,
      "team_a_score": 1,
      "round": 12,
      "minutes": 90,
      "goals_scored": 0,
      "assists": 0,
      "clean_sheets": 0,
      "goals_conceded": 5,
      "penalties_saved": 0,
      "penalties_missed": 0,
      "yellow_cards": 0,
      "red_cards": 0,
      "saves": 0,
      "own_goals": 0,
      "attacking_bonus": 0,
      "defending_bonus": 0,
      "winning_goals": 0,
      "key_passes": 1,
      "clearances_blocks_interceptions": 4,
      "value": 83,
      "transfers_balance": -218,
      "selected": 4938,
      "transfers_in": 34,
      "transfers_out": 252
    },
    {
      "element": 210,
      "fixture": 104,
      "opponent_team": 7,
      "total_points": 2,
      "was_home": true,
      "kickoff_time": "2024-07-08T17:00:00Z",
      "team_h_score": 1,
      "team_a_score": 3,
      "round": 13,
      "minutes": 75,
      "goals_scored": 0,
      "assists": 0,
      "clean_sheets": 0,
      "goals_conceded": 3,
      "penalties_saved": 0,
      "penalties_missed": 0,
      "yellow_cards": 0,
      "red_cards": 0,
      "saves": 0,
      "own_goals": 0,
      "attacking_bonus": 0,
      "defending_bonus": 0,
      "winning_goals": 0,
      "key_passes": 0,
      "clearances_blocks_interceptions": 4,
      "value": 83,
      "transfers_balance": -173,
      "selected": 4791,
      "transfers_in": 8,
      "transfers_out": 181
    },
    {
      "element": 210,
      "fixture": 114,
      "opponent_team": 30,
      "total_points": 2,
      "was_home": false,
      "kickoff_time": "2024-07-14T14:30:00Z",
      "team_h_score": 2,
      "team_a_score": 1,
      "round": 14,
      "minutes": 90,
      "goals_scored": 0,
      "assists": 0,
      "clean_sheets": 0,
      "goals_conceded": 2,
      "penalties_saved": 0,
      "penalties_missed": 0,
      "yellow_cards": 0,
      "red_cards": 0,
      "saves": 0,
      "own_goals": 0,
      "attacking_bonus": 0,
      "defending_bonus": 0,
      "winning_goals": 0,
      "key_passes": 1,
      "clearances_blocks_interceptions": 4,
      "value": 83,
      "transfers_balance": -78,
      "selected": 4722,
      "transfers_in": 35,
      "transfers_out": 113
    },
    {
      "element": 210,
      "fixture": 120,
      "opponent_team": 15,
      "total_points": 8,
      "was_home": true,
      "kickoff_time": "2024-07-21T12:00:00Z",
      "team_h_score": 1,
      "team_a_score": 0,
      "round": 15,
      "minutes": 61,
      "goals_scored": 1,
      "assists": 0,
      "clean_sheets": 1,
      "goals_conceded": 0,
      "penalties_saved": 0,
      "penalties_missed": 0,
      "yellow_cards": 0,
      "red_cards": 0,
      "saves": 0,
      "own_goals": 0,
      "attacking_bonus": 0,
      "defending_bonus": 0,
      "winning_goals": 1,
      "key_passes": 0,
      "clearances_blocks_interceptions": 4,
      "value": 83,
      "transfers_balance": -44,
      "selected": 4682,
      "transfers_in": 67,
      "transfers_out": 111
    },
    {
      "element": 210,
      "fixture": 130,
      "opponent_team": 10,
      "total_points": 11,
      "was_home": true,
      "kickoff_time": "2024-07-27T13:00:00Z",
      "team_h_score": 2,
      "team_a_score": 0,
      "round": 16,
      "minutes": 84,
      "goals_scored": 2,
      "assists": 0,
      "clean_sheets": 1,
      "goals_conceded": 0,
      "penalties_saved": 0,
      "penalties_missed": 1,
      "yellow_cards": 0,
      "red_cards": 0,
      "saves": 0,
      "own_goals": 0,
      "attacking_bonus": 0,
      "defending_bonus": 0,
      "winning_goals": 1,
      "key_passes": 1,
      "clearances_blocks_interceptions": 4,
      "value": 83,
      "transfers_balance": 83,
      "selected": 4770,
      "transfers_in": 143,
      "transfers_out": 60
    },
    {
      "element": 210,
      "fixture": 133,
      "opponent_team": 31,
      "total_points": 2,
      "was_home": false,
      "kickoff_time": "2024-08-03T13:00:00Z",
      "team_h_score": 0,
      "team_a_score": 1,
      "round": 17,
      "minutes": 90,
      "goals_scored": 0,
      "assists": 0,
      "clean_sheets": 1,
      "goals_conceded": 0,
      "penalties_saved": 0,
      "penalties_missed": 0,
      "yellow_cards": 0,
      "red_cards": 0,
      "saves": 0,
      "own_goals": 0,
      "attacking_bonus": 0,
      "defending_bonus": 0,
      "winning_goals": 0,
      "key_passes": 1,
      "clearances_blocks_interceptions": 5,
      "value": 83,
      "transfers_balance": 835,
      "selected": 6833,
      "transfers_in": 925,
      "transfers_out": 90
    },
    {
      "element": 210,
      "fixture": 143,
      "opponent_team": 30,
      "total_points": 0,
      "was_home": true,
      "kickoff_time": "2024-08-10T13:00:00Z",
      "team_h_score": 2,
      "team_a_score": 1,
      "round": 18,
      "minutes": 0,
      "goals_scored": 0,
      "assists": 0,
      "clean_sheets": 0,
      "goals_conceded": 0,
      "penalties_saved": 0,
      "penalties_missed": 0,
      "yellow_cards": 0,
      "red_cards": 0,
      "saves": 0,
      "own_goals": 0,
      "attacking_bonus": 0,
      "defending_bonus": 0,
      "winning_goals": 0,
      "key_passes": 0,
      "clearances_blocks_interceptions": 0,
      "value": 84,
      "transfers_balance": 814,
      "selected": 6494,
      "transfers_in": 1195,
      "transfers_out": 381
    },
    {
      "element": 210,
      "fixture": 149,
      "opponent_team": 1,
      "total_points": 2,
      "was_home": false,
      "kickoff_time": "2024-08-17T13:00:00Z",
      "team_h_score": 2,
      "team_a_score": 1,
      "round": 19,
      "minutes": 90,
      "goals_scored": 0,
      "assists": 0,
      "clean_sheets": 0,
      "goals_conceded": 2,
      "penalties_saved": 0,
      "penalties_missed": 0,
      "yellow_cards": 0,
      "red_cards": 0,
      "saves": 0,
      "own_goals": 0,
      "attacking_bonus": 0,
      "defending_bonus": 0,
      "winning_goals": 0,
      "key_passes": 1,
      "clearances_blocks_interceptions": 4,
      "value": 84,
      "transfers_balance": -303,
      "selected": 6112,
      "transfers_in": 102,
      "transfers_out": 405
    },
    {
      "element": 210,
      "fixture": 159,
      "opponent_team": 14,
      "total_points": 7,
      "was_home": true,
      "kickoff_time": "2024-08-26T17:00:00Z",
      "team_h_score": 1,
      "team_a_score": 2,
      "round": 20,
      "minutes": 90,
      "goals_scored": 1,
      "assists": 0,
      "clean_sheets": 0,
      "goals_conceded": 2,
      "penalties_saved": 0,
      "penalties_missed": 0,
      "yellow_cards": 0,
      "red_cards": 0,
      "saves": 0,
      "own_goals": 0,
      "attacking_bonus": 0,
      "defending_bonus": 0,
      "winning_goals": 0,
      "key_passes": 0,
      "clearances_blocks_interceptions": 3,
      "value": 84,
      "transfers_balance": -74,
      "selected": 6038,
      "transfers_in": 157,
      "transfers_out": 231
    },
    {
      "element": 210,
      "fixture": 166,
      "opponent_team": 6,
      "total_points": 12,
      "was_home": true,
      "kickoff_time": "2024-09-01T14:30:00Z",
      "team_h_score": 3,
      "team_a_score": 3,
      "round": 21,
      "minutes": 90,
      "goals_scored": 2,
      "assists": 0,
      "clean_sheets": 0,
      "goals_conceded": 3,
      "penalties_saved": 0,
      "penalties_missed": 0,
      "yellow_cards": 0,
      "red_cards": 0,
      "saves": 0,
      "own_goals": 0,
      "attacking_bonus": 0,
      "defending_bonus": 0,
      "winning_goals": 0,
      "key_passes": 0,
      "clearances_blocks_interceptions": 3,
      "value": 84,
      "transfers_balance": -46,
      "selected": 6006,
      "transfers_in": 145,
      "transfers_out": 191
    },
    {
      "element": 210,
      "fixture": 172,
      "opponent_team": 2,
      "total_points": 2,
      "was_home": false,
      "kickoff_time": "2024-09-16T17:10:00Z",
      "team_h_score": 1,
      "team_a_score": 1,
      "round": 22,
      "minutes": 62,
      "goals_scored": 0,
      "assists": 0,
      "clean_sheets": 0,
      "goals_conceded": 1,
      "penalties_saved": 0,
      "penalties_missed": 0,
      "yellow_cards": 0,
      "red_cards": 0,
      "saves": 0,
      "own_goals": 0,
      "attacking_bonus": 0,
      "defending_bonus": 0,
      "winning_goals": 0,
      "key_passes": 0,
      "clearances_blocks_interceptions": 3,
      "value": 84,
      "transfers_balance": 305,
      "selected": 6566,
      "transfers_in": 430,
      "transfers_out": 125
    },
    {
      "element": 210,
      "fixture": 186,
      "opponent_team": 5,
      "total_points": 0,
      "was_home": false,
      "kickoff_time": "2024-09-19T17:00:00Z",
      "team_h_score": 2,
      "team_a_score": 2,
      "round": 22,
      "minutes": 0,
      "goals_scored": 0,
      "assists": 0,
      "clean_sheets": 0,
      "goals_conceded": 0,
      "penalties_saved": 0,
      "penalties_missed": 0,
      "yellow_cards": 0,
      "red_cards": 0,
      "saves": 0,
      "own_goals": 0,
      "attacking_bonus": 0,
      "defending_bonus": 0,
      "winning_goals": 0,
      "key_passes": 0,
      "clearances_blocks_interceptions": 0,
      "value": 84,
      "transfers_balance": 305,
      "selected": 6566,
      "transfers_in": 430,
      "transfers_out": 125
    },
    {
      "element": 210,
      "fixture": 195,
      "opponent_team": 15,
      "total_points": 0,
      "was_home": false,
      "kickoff_time": "2024-09-29T12:00:00Z",
      "team_h_score": 0,
      "team_a_score": 0,
      "round": 25,
      "minutes": 0,
      "goals_scored": 0,
      "assists": 0,
      "clean_sheets": 0,
      "goals_conceded": 0,
      "penalties_saved": 0,
      "penalties_missed": 0,
      "yellow_cards": 0,
      "red_cards": 0,
      "saves": 0,
      "own_goals": 0,
      "attacking_bonus": 0,
      "defending_bonus": 0,
      "winning_goals": 0,
      "key_passes": 0,
      "clearances_blocks_interceptions": 0,
      "value": 84,
      "transfers_balance": -208,
      "selected": 4661,
      "transfers_in": 5,
      "transfers_out": 213
    },
    {
      "element": 210,
      "fixture": 183,
      "opponent_team": 3,
      "total_points": 0,
      "was_home": true,
      "kickoff_time": "2024-10-03T17:00:00Z",
      "team_h_score": 0,
      "team_a_score": 2,
      "round": 25,
      "minutes": 0,
      "goals_scored": 0,
      "assists": 0,
      "clean_sheets": 0,
      "goals_conceded": 0,
      "penalties_saved": 0,
      "penalties_missed": 0,
      "yellow_cards": 0,
      "red_cards": 0,
      "saves": 0,
      "own_goals": 0,
      "attacking_bonus": 0,
      "defending_bonus": 0,
      "winning_goals": 0,
      "key_passes": 0,
      "clearances_blocks_interceptions": 0,
      "value": 84,
      "transfers_balance": -208,
      "selected": 4661,
      "transfers_in": 5,
      "transfers_out": 213
    },
    {
      "element": 210,
      "fixture": 207,
      "opponent_team": 4,
      "total_points": 0,
      "was_home": true,
      "kickoff_time": "2024-10-06T14:30:00Z",
      "team_h_score": 0,
      "team_a_score": 2,
      "round": 26,
      "minutes": 0,
      "goals_scored": 0,
      "assists": 0,
      "clean_sheets": 0,
      "goals_conceded": 0,
      "penalties_saved": 0,
      "penalties_missed": 0,
      "yellow_cards": 0,
      "red_cards": 0,
      "saves": 0,
      "own_goals": 0,
      "attacking_bonus": 0,
      "defending_bonus": 0,
      "winning_goals": 0,
      "key_passes": 0,
      "clearances_blocks_interceptions": 0,
      "value": 84,
      "transfers_balance": -100,
      "selected": 4571,
      "transfers_in": 2,
      "transfers_out": 102
    },
    {
      "element": 210,
      "fixture": 215,
      "opponent_team": 21,
      "total_points": 1,
      "was_home": true,
      "kickoff_time": "2024-10-21T17:00:00Z",
      "team_h_score": 1,
      "team_a_score": 1,
      "round": 27,
      "minutes": 90,
      "goals_scored": 0,
      "assists": 0,
      "clean_sheets": 0,
      "goals_conceded": 1,
      "penalties_saved": 0,
      "penalties_missed": 0,
      "yellow_cards": 1,
      "red_cards": 0,
      "saves": 0,
      "own_goals": 0,
      "attacking_bonus": 0,
      "defending_bonus": 0,
      "winning_goals": 0,
      "key_passes": 1,
      "clearances_blocks_interceptions": 2,
      "value": 83,
      "transfers_balance": -49,
      "selected": 4522,
      "transfers_in": 16,
      "transfers_out": 65
    },
    {
      "element": 210,
      "fixture": 224,
      "opponent_team": 18,
      "total_points": 7,
      "was_home": false,
      "kickoff_time": "2024-10-27T13:00:00Z",
      "team_h_score": 1,
      "team_a_score": 2,
      "round": 28,
      "minutes": 78,
      "goals_scored": 1,
      "assists": 0,
      "clean_sheets": 1,
      "goals_conceded": 0,
      "penalties_saved": 0,
      "penalties_missed": 0,
      "yellow_cards": 0,
      "red_cards": 0,
      "saves": 0,
      "own_goals": 0,
      "attacking_bonus": 0,
      "defending_bonus": 0,
      "winning_goals": 0,
      "key_passes": 1,
      "clearances_blocks_interceptions": 7,
      "value": 83,
      "transfers_balance": 92,
      "selected": 4624,
      "transfers_in": 109,
      "transfers_out": 17
    },
    {
      "element": 210,
      "fixture": 231,
      "opponent_team": 12,
      "total_points": 0,
      "was_home": true,
      "kickoff_time": "2024-11-04T18:10:00Z",
      "team_h_score": null,
      "team_a_score": null,
      "round": 29,
      "minutes": 0,
      "goals_scored": 0,
      "assists": 0,
      "clean_sheets": 0,
      "goals_conceded": 0,
      "penalties_saved": 0,
      "penalties_missed": 0,
      "yellow_cards": 0,
      "red_cards": 0,
      "saves": 0,
      "own_goals": 0,
      "attacking_bonus": 0,
      "defending_bonus": 0,
      "winning_goals": 0,
      "key_passes": 0,
      "clearances_blocks_interceptions": 0,
      "value": 83,
      "transfers_balance": 213,
      "selected": 4842,
      "transfers_in": 228,
      "transfers_out": 15
    }
  ],
  "history_past": [
    {
      "season_name": "2019",
      "element_code": 95922,
      "start_cost": 100,
      "end_cost": 98,
      "total_points": 103,
      "minutes": 1986,
      "goals_scored": 10,
      "assists": 3,
      "clean_sheets": 14,
      "goals_conceded": 16,
      "penalties_saved": 0,
      "penalties_missed": 0,
      "yellow_cards": 2,
      "red_cards": 0,
      "saves": 0,
      "own_goals": 0,
      "attacking_bonus": 0,
      "defending_bonus": 0,
      "winning_goals": 0,
      "key_passes": 25,
      "clearances_blocks_interceptions": 12
    },
    {
      "season_name": "2020",
      "element_code": 95922,
      "start_cost": 95,
      "end_cost": 104,
      "total_points": 138,
      "minutes": 2273,
      "goals_scored": 18,
      "assists": 3,
      "clean_sheets": 7,
      "goals_conceded": 40,
      "penalties_saved": 0,
      "penalties_missed": 0,
      "yellow_cards": 0,
      "red_cards": 0,
      "saves": 0,
      "own_goals": 0,
      "attacking_bonus": 3,
      "defending_bonus": 0,
      "winning_goals": 0,
      "key_passes": 23,
      "clearances_blocks_interceptions": 19
    },
    {
      "season_name": "2021",
      "element_code": 95922,
      "start_cost": 100,
      "end_cost": 98,
      "total_points": 48,
      "minutes": 868,
      "goals_scored": 5,
      "assists": 0,
      "clean_sheets": 1,
      "goals_conceded": 13,
      "penalties_saved": 0,
      "penalties_missed": 1,
      "yellow_cards": 1,
      "red_cards": 0,
      "saves": 0,
      "own_goals": 0,
      "attacking_bonus": 2,
      "defending_bonus": 0,
      "winning_goals": 0,
      "key_passes": 14,
      "clearances_blocks_interceptions": 15
    },
    {
      "season_name": "2022",
      "element_code": 95922,
      "start_cost": 95,
      "end_cost": 94,
      "total_points": 116,
      "minutes": 2250,
      "goals_scored": 11,
      "assists": 2,
      "clean_sheets": 6,
      "goals_conceded": 30,
      "penalties_saved": 0,
      "penalties_missed": 1,
      "yellow_cards": 2,
      "red_cards": 0,
      "saves": 0,
      "own_goals": 0,
      "attacking_bonus": 3,
      "defending_bonus": 1,
      "winning_goals": 2,
      "key_passes": 16,
      "clearances_blocks_interceptions": 94
    },
    {
      "season_name": "2023",
      "element_code": 95922,
      "start_cost": 90,
      "end_cost": 96,
      "total_points": 102,
      "minutes": 2075,
      "goals_scored": 8,
      "assists": 3,
      "clean_sheets": 5,
      "goals_conceded": 34,
      "penalties_saved": 0,
      "penalties_missed": 0,
      "yellow_cards": 3,
      "red_cards": 0,
      "saves": 0,
      "own_goals": 1,
      "attacking_bonus": 2,
      "defending_bonus": 2,
      "winning_goals": 4,
      "key_passes": 10,
      "clearances_blocks_interceptions": 80
    }
  ]
}