{
  "fixtures": [
    {
      "id": 186,
      "code": 2496467,
      "team_h": 2,
      "team_h_score": null,
      "team_a": 6,
      "team_a_score": null,
      "event": 24,
      "finished": false,
      "minutes": 0,
      "provisional_start_time": false,
      "kickoff_time": "2025-09-21T12:00:00Z",
      "event_name": "Omg\u00e5ng 24",
      "is_home": false
    },
    {
      "id": 198,
      "code": 2496479,
      "team_h": 6,
      "team_h_score": null,
      "team_a": 9,
      "team_a_score": null,
      "event": 25,
      "finished": false,
      "minutes": 0,
      "provisional_start_time": false,
      "kickoff_time": "2025-09-27T15:30:00Z",
      "event_name": "Omg\u00e5ng 25",
      "is_home": true
    },
    {
      "id": 202,
      "code": 2496484,
      "team_h": 21,
      "team_h_score": null,
      "team_a": 6,
      "team_a_score": null,
      "event": 26,
      "finished": false,
      "minutes": 0,
      "provisional_start_time": false,
      "kickoff_time": "2025-10-05T14:30:00Z",
      "event_name": "Omg\u00e5ng 26",
      "is_home": false
    },
    {
      "id": 213,
      "code": 2496495,
      "team_h": 6,
      "team_h_score": null,
      "team_a": 3,
      "team_a_score": null,
      "event": 27,
      "finished": false,
      "minutes": 0,
      "provisional_start_time": false,
      "kickoff_time": "2025-10-18T15:30:00Z",
      "event_name": "Omg\u00e5ng 27",
      "is_home": true
    },
    {
      "id": 217,
      "code": 2496499,
      "team_h": 12,
      "team_h_score": null,
      "team_a": 6,
      "team_a_score": null,
      "event": 28,
      "finished": false,
      "minutes": 0,
      "provisional_start_time": false,
      "kickoff_time": "2025-10-26T15:30:00Z",
      "event_name": "Omg\u00e5ng 28",
      "is_home": false
    },
    {
      "id": 230,
      "code": 2496510,
      "team_h": 6,
      "team_h_score": null,
      "team_a": 1,
      "team_a_score": null,
      "event": 29,
      "finished": false,
      "minutes": 0,
      "provisional_start_time": false,
      "kickoff_time": "2025-11-01T14:00:00Z",
      "event_name": "Omg\u00e5ng 29",
      "is_home": true
    },
    {
      "id": 238,
      "code": 2496521,
      "team_h": 14,
      "team_h_score": null,
      "team_a": 6,
      "team_a_score": null,
      "event": 30,
      "finished": false,
      "minutes": 0,
      "provisional_start_time": false,
      "kickoff_time": "2025-11-09T14:00:00Z",
      "event_name": "Omg\u00e5ng 30",
      "is_home": false
    }
  ],
  "history": [
    {
      "element": 460,
      "fixture": 116,
      "opponent_team": 15,
      "total_points": 1,
      "was_home": true,
      "kickoff_time": "2025-07-13T16:30:00Z",
      "team_h_score": 4,
      "team_a_score": 1,
      "round": 15,
      "modified": false,
      "minutes": 21,
      "goals_scored": 0,
      "assists": 0,
      "clean_sheets": 0,
      "goals_conceded": 1,
      "penalties_saved": 0,
      "penalties_missed": 0,
      "yellow_cards": 0,
      "red_cards": 0,
      "saves": 0,
      "own_goals": 0,
      "attacking_bonus": 0,
      "defending_bonus": 0,
      "winning_goals": 0,
      "key_passes": 0,
      "clearances_blocks_interceptions": 0,
      "value": 50,
      "transfers_balance": 2,
      "selected": 2,
      "transfers_in": 2,
      "transfers_out": 0
    },
    {
      "element": 460,
      "fixture": 123,
      "opponent_team": 15,
      "total_points": 1,
      "was_home": false,
      "kickoff_time": "2025-07-20T14:30:00Z",
      "team_h_score": 0,
      "team_a_score": 0,
      "round": 16,
      "modified": false,
      "minutes": 58,
      "goals_scored": 0,
      "assists": 0,
      "clean_sheets": 0,
      "goals_conceded": 0,
      "penalties_saved": 0,
      "penalties_missed": 0,
      "yellow_cards": 0,
      "red_cards": 0,
      "saves": 0,
      "own_goals": 0,
      "attacking_bonus": 0,
      "defending_bonus": 0,
      "winning_goals": 0,
      "key_passes": 0,
      "clearances_blocks_interceptions": 2,
      "value": 50,
      "transfers_balance": 0,
      "selected": 2,
      "transfers_in": 0,
      "transfers_out": 0
    },
    {
      "element": 460,
      "fixture": 134,
      "opponent_team": 7,
      "total_points": 0,
      "was_home": true,
      "kickoff_time": "2025-07-27T12:00:00Z",
      "team_h_score": 1,
      "team_a_score": 6,
      "round": 17,
      "modified": false,
      "minutes": 0,
      "goals_scored": 0,
      "assists": 0,
      "clean_sheets": 0,
      "goals_conceded": 0,
      "penalties_saved": 0,
      "penalties_missed": 0,
      "yellow_cards": 0,
      "red_cards": 0,
      "saves": 0,
      "own_goals": 0,
      "attacking_bonus": 0,
      "defending_bonus": 0,
      "winning_goals": 0,
      "key_passes": 0,
      "clearances_blocks_interceptions": 0,
      "value": 50,
      "transfers_balance": 1,
      "selected": 3,
      "transfers_in": 1,
      "transfers_out": 0
    },
    {
      "element": 460,
      "fixture": 140,
      "opponent_team": 5,
      "total_points": 5,
      "was_home": true,
      "kickoff_time": "2025-08-03T12:00:00Z",
      "team_h_score": 1,
      "team_a_score": 2,
      "round": 18,
      "modified": false,
      "minutes": 69,
      "goals_scored": 0,
      "assists": 0,
      "clean_sheets": 1,
      "goals_conceded": 0,
      "penalties_saved": 0,
      "penalties_missed": 0,
      "yellow_cards": 0,
      "red_cards": 0,
      "saves": 0,
      "own_goals": 0,
      "attacking_bonus": 1,
      "defending_bonus": 1,
      "winning_goals": 0,
      "key_passes": 3,
      "clearances_blocks_interceptions": 9,
      "value": 50,
      "transfers_balance": 0,
      "selected": 3,
      "transfers_in": 0,
      "transfers_out": 0
    },
    {
      "element": 460,
      "fixture": 146,
      "opponent_team": 16,
      "total_points": 0,
      "was_home": false,
      "kickoff_time": "2025-08-10T12:00:00Z",
      "team_h_score": 0,
      "team_a_score": 0,
      "round": 19,
      "modified": false,
      "minutes": 0,
      "goals_scored": 0,
      "assists": 0,
      "clean_sheets": 0,
      "goals_conceded": 0,
      "penalties_saved": 0,
      "penalties_missed": 0,
      "yellow_cards": 0,
      "red_cards": 0,
      "saves": 0,
      "own_goals": 0,
      "attacking_bonus": 0,
      "defending_bonus": 0,
      "winning_goals": 0,
      "key_passes": 0,
      "clearances_blocks_interceptions": 0,
      "value": 50,
      "transfers_balance": 2,
      "selected": 6,
      "transfers_in": 3,
      "transfers_out": 1
    },
    {
      "element": 460,
      "fixture": 156,
      "opponent_team": 26,
      "total_points": 0,
      "was_home": true,
      "kickoff_time": "2025-08-17T14:30:00Z",
      "team_h_score": 0,
      "team_a_score": 2,
      "round": 20,
      "modified": false,
      "minutes": 0,
      "goals_scored": 0,
      "assists": 0,
      "clean_sheets": 0,
      "goals_conceded": 0,
      "penalties_saved": 0,
      "penalties_missed": 0,
      "yellow_cards": 0,
      "red_cards": 0,
      "saves": 0,
      "own_goals": 0,
      "attacking_bonus": 0,
      "defending_bonus": 0,
      "winning_goals": 0,
      "key_passes": 0,
      "clearances_blocks_interceptions": 0,
      "value": 50,
      "transfers_balance": 0,
      "selected": 5,
      "transfers_in": 0,
      "transfers_out": 0
    },
    {
      "element": 460,
      "fixture": 167,
      "opponent_team": 18,
      "total_points": 0,
      "was_home": false,
      "kickoff_time": "2025-08-24T14:30:00Z",
      "team_h_score": 1,
      "team_a_score": 5,
      "round": 21,
      "modified": false,
      "minutes": 0,
      "goals_scored": 0,
      "assists": 0,
      "clean_sheets": 0,
      "goals_conceded": 0,
      "penalties_saved": 0,
      "penalties_missed": 0,
      "yellow_cards": 0,
      "red_cards": 0,
      "saves": 0,
      "own_goals": 0,
      "attacking_bonus": 0,
      "defending_bonus": 0,
      "winning_goals": 0,
      "key_passes": 0,
      "clearances_blocks_interceptions": 0,
      "value": 50,
      "transfers_balance": 0,
      "selected": 5,
      "transfers_in": 0,
      "transfers_out": 0
    },
    {
      "element": 460,
      "fixture": 171,
      "opponent_team": 30,
      "total_points": 1,
      "was_home": false,
      "kickoff_time": "2025-08-31T14:30:00Z",
      "team_h_score": 2,
      "team_a_score": 1,
      "round": 22,
      "modified": false,
      "minutes": 45,
      "goals_scored": 0,
      "assists": 0,
      "clean_sheets": 0,
      "goals_conceded": 1,
      "penalties_saved": 0,
      "penalties_missed": 0,
      "yellow_cards": 0,
      "red_cards": 0,
      "saves": 0,
      "own_goals": 0,
      "attacking_bonus": 0,
      "defending_bonus": 0,
      "winning_goals": 0,
      "key_passes": 0,
      "clearances_blocks_interceptions": 3,
      "value": 50,
      "transfers_balance": -1,
      "selected": 4,
      "transfers_in": 0,
      "transfers_out": 1
    },
    {
      "element": 460,
      "fixture": 182,
      "opponent_team": 4,
      "total_points": 0,
      "was_home": true,
      "kickoff_time": "2025-09-15T17:10:00Z",
      "team_h_score": 1,
      "team_a_score": 2,
      "round": 23,
      "modified": false,
      "minutes": 0,
      "goals_scored": 0,
      "assists": 0,
      "clean_sheets": 0,
      "goals_conceded": 0,
      "penalties_saved": 0,
      "penalties_missed": 0,
      "yellow_cards": 0,
      "red_cards": 0,
      "saves": 0,
      "own_goals": 0,
      "attacking_bonus": 0,
      "defending_bonus": 0,
      "winning_goals": 0,
      "key_passes": 0,
      "clearances_blocks_interceptions": 0,
      "value": 50,
      "transfers_balance": -1,
      "selected": 3,
      "transfers_in": 0,
      "transfers_out": 1
    },
    {
      "element": 460,
      "fixture": 186,
      "opponent_team": 2,
      "total_points": 0,
      "was_home": false,
      "kickoff_time": "2025-09-21T12:00:00Z",
      "team_h_score": null,
      "team_a_score": null,
      "round": 24,
      "modified": false,
      "minutes": 0,
      "goals_scored": 0,
      "assists": 0,
      "clean_sheets": 0,
      "goals_conceded": 0,
      "penalties_saved": 0,
      "penalties_missed": 0,
      "yellow_cards": 0,
      "red_cards": 0,
      "saves": 0,
      "own_goals": 0,
      "attacking_bonus": 0,
      "defending_bonus": 0,
      "winning_goals": 0,
      "key_passes": 0,
      "clearances_blocks_interceptions": 0,
      "value": 50,
      "transfers_balance": 0,
      "selected": 3,
      "transfers_in": 0,
      "transfers_out": 0
    }
  ],
  "history_past": []
}